snucovery/__init__.py
snucovery/aws.py
snucovery/cli.py
snucovery/errors.py
snucovery/excel.py
snucovery-0.1.3.dist-info/entry_points.txt
snucovery-0.1.3.dist-info/LICENSE.md
snucovery-0.1.3.dist-info/WHEEL
snucovery-0.1.3.dist-info/METADATA
snucovery-0.1.3.dist-info/RECORD
