Metadata-Version: 2.1
Name: snucovery
Version: 0.1.3
Summary: Command Line utility to collect Aws Asset Data and export to Excel Stylesheets
Author: Johnny Martin
Author-email: johnny.martin@tylertech.com
Requires-Python: >=3.7,<4.0
Classifier: Programming Language :: Python :: 3
Classifier: Programming Language :: Python :: 3.7
Requires-Dist: boto3 (>=1.9,<2.0)
Requires-Dist: pyjq (>=2.3,<3.0)
Requires-Dist: xlsxwriter (>=1.1,<2.0)
